uom_project/__init__.py
uom_project/_modidx.py
uom_project/core.py
uom_project/poisson_solvers.py
uom_project/streamfunction_vorticity.py
uom_project/streamfunction_vorticity_jax.py
uom_project/streamfunction_vorticity_newton.py
uom_project/streamfunction_vorticity_pytorch.py
uom_project-0.0.5.dist-info/LICENSE
uom_project-0.0.5.dist-info/METADATA
uom_project-0.0.5.dist-info/WHEEL
uom_project-0.0.5.dist-info/entry_points.txt
uom_project-0.0.5.dist-info/top_level.txt
uom_project-0.0.5.dist-info/RECORD
